syx_PYC/__init__.py
syx_PYC-0.0.1.dist-info/LICENSE.txt
syx_PYC-0.0.1.dist-info/METADATA
syx_PYC-0.0.1.dist-info/WHEEL
syx_PYC-0.0.1.dist-info/top_level.txt
syx_PYC-0.0.1.dist-info/RECORD
